pyapollo/__init__.py
pyapollo/client.py
pyapollo/config.py
pyapollo/exception.py
pyapollox-0.1.7.dist-info/WHEEL
pyapollox-0.1.7.dist-info/METADATA
pyapollox-0.1.7.dist-info/licenses/LICENSE
pyapollox-0.1.7.dist-info/RECORD
