Metadata-Version: 2.1
Name: pyapollox
Version: 0.1.7
License: MIT
Author-email: fatelei <fatelei@gmail.com>
Requires-Python: >=3.10
Requires-Dist: httpx>=0.27.0
